finalsa/dynamo/client/__init__.py
finalsa/dynamo/client/client/__init__.py
finalsa/dynamo/client/client/async_client.py
finalsa/dynamo/client/client/async_implementation.py
finalsa/dynamo/client/client/client.py
finalsa/dynamo/client/client/implementation.py
finalsa/dynamo/client/interface/__init__.py
finalsa/dynamo/client/interface/async_client.py
finalsa/dynamo/client/interface/client.py
finalsa/dynamo/client/tests/__init__.py
finalsa/dynamo/client/tests/async_client.py
finalsa/dynamo/client/tests/client.py
finalsa/dynamo/client/tests/implementation.py
finalsa_dynamo_client-1.0.0.dist-info/METADATA
finalsa_dynamo_client-1.0.0.dist-info/WHEEL
finalsa_dynamo_client-1.0.0.dist-info/licenses/LICENSE.md
finalsa_dynamo_client-1.0.0.dist-info/RECORD
