Metadata-Version: 2.4
Name: finalsa-dynamo-client
Version: 1.0.0
Summary: A simple DynamoDB client for Python
Project-URL: Homepage, https://github.com/finalsa/finalsa-dynamo-client
Author-email: Luis Jimenez <luis@finalsa.com>
License: MIT License
License-File: LICENSE.md
Keywords: aws,client,dynamodb
Requires-Python: >=3.10
Requires-Dist: boto3>=1.38.18
